{
  "_class": "symbolInstance",
  "booleanOperation": -1,
  "clippingMaskMode": 0,
  "do_objectID": "7D93F86B-27A1-4D1A-AD0E-3535ED6104A9",
  "exportOptions": {
    "_class": "exportOptions",
    "do_objectID": "6D77D230-8A9D-40BB-9B70-F9C7E36207AA",
    "exportFormats": [
    ],
    "includedLayerIds": [
    ],
    "layerOptions": 0,
    "shouldTrim": false
  },
  "frame": {
    "_class": "rect",
    "constrainProportions": false,
    "do_objectID": "A0ADB3F2-9A01-4D9F-833B-CC78659D7681",
    "height": 100,
    "width": 960,
    "x": 0,
    "y": 495
  },
  "hasClippingMask": false,
  "horizontalSpacing": 0,
  "isFixedToViewport": false,
  "isFlippedHorizontal": false,
  "isFlippedVertical": false,
  "isLocked": false,
  "isVisible": true,
  "layerListExpandedType": 2,
  "name": "wireframes/concerts/entry",
  "nameIsFixed": false,
  "overrideValues": [
    {
      "_class": "overrideValue",
      "do_objectID": "81A752F9-9E26-4D03-915C-C97839B96CB0",
      "overrideName": "C57FD6BF-CFE8-4E13-BC57-734386343C00_stringValue",
      "value": "Tickets"
    }
  ],
  "resizingConstraint": 63,
  "resizingType": 0,
  "rotation": 0,
  "scale": 1,
  "shouldBreakMaskChain": false,
  "style": {
    "_class": "style",
    "do_objectID": "F4340F55-185F-4944-827C-9086C4A8DCB9",
    "endMarkerType": 0,
    "miterLimit": 10,
    "startMarkerType": 0,
    "windingRule": 1
  },
  "symbolID": "7B018224-5994-455A-A56E-07AF9E5290F6",
  "verticalSpacing": 0
}