{
  "_class": "shapePath",
  "booleanOperation": -1,
  "clippingMaskMode": 0,
  "do_objectID": "3A56630B-047A-4356-B8D8-96F6EB917B85",
  "edited": true,
  "exportOptions": {
    "_class": "exportOptions",
    "do_objectID": "CB4C2E66-3FE0-479E-8E0F-8AE48FAE7EC5",
    "exportFormats": [
    ],
    "includedLayerIds": [
    ],
    "layerOptions": 0,
    "shouldTrim": false
  },
  "frame": {
    "_class": "rect",
    "constrainProportions": false,
    "do_objectID": "1AC3F7C6-6C2F-4E87-9AB2-84536D5EAF5B",
    "height": 5.502016000000005,
    "width": 15.37984000000001,
    "x": 8.533333333333335,
    "y": 9.599999999999998
  },
  "hasClippingMask": false,
  "isClosed": true,
  "isFixedToViewport": false,
  "isFlippedHorizontal": false,
  "isFlippedVertical": false,
  "isLocked": false,
  "isVisible": true,
  "layerListExpandedType": 0,
  "maintainScrollPosition": false,
  "name": "Combined-Shape-path",
  "nameIsFixed": false,
  "pointRadiusBehaviour": 1,
  "points": [
    {
      "_class": "curvePoint",
      "cornerRadius": 0,
      "curveFrom": "{0.58516083392284968, 1}",
      "curveMode": 2,
      "curveTo": "{0.41870916732553781, 1}",
      "hasCurveFrom": true,
      "hasCurveTo": true,
      "point": "{0.49997919354167525, 1}"
    },
    {
      "_class": "curvePoint",
      "cornerRadius": 0,
      "curveFrom": "{0.99933419333361062, 0.34896299829008148}",
      "curveMode": 4,
      "curveTo": "{0.99933419333361062, 0.34896299829008148}",
      "hasCurveFrom": false,
      "hasCurveTo": true,
      "point": "{0.99933419333361062, 0.34896299829008148}"
    },
    {
      "_class": "curvePoint",
      "cornerRadius": 0,
      "curveFrom": "{1, 0.10422361548930419}",
      "curveMode": 4,
      "curveTo": "{1, 0.2326419988600541}",
      "hasCurveFrom": true,
      "hasCurveTo": false,
      "point": "{1, 0.2326419988600541}"
    },
    {
      "_class": "curvePoint",
      "cornerRadius": 0,
      "curveFrom": "{0.91664932795139598, 0}",
      "curveMode": 4,
      "curveTo": "{0.9627148266822021, 0}",
      "hasCurveFrom": false,
      "hasCurveTo": true,
      "point": "{0.91664932795139598, 0}"
    },
    {
      "_class": "curvePoint",
      "cornerRadius": 0,
      "curveFrom": "{0.0372851733177978, 0}",
      "curveMode": 4,
      "curveTo": "{0.083309059131954549, 0}",
      "hasCurveFrom": true,
      "hasCurveTo": false,
      "point": "{0.083309059131954549, 0}"
    },
    {
      "_class": "curvePoint",
      "cornerRadius": 0,
      "curveFrom": "{0, 0.2326419988600541}",
      "curveMode": 4,
      "curveTo": "{0, 0.10422361548930419}",
      "hasCurveFrom": false,
      "hasCurveTo": true,
      "point": "{0, 0.2326419988600541}"
    },
    {
      "_class": "curvePoint",
      "cornerRadius": 0,
      "curveFrom": "{0, 0.33628400935220848}",
      "curveMode": 4,
      "curveTo": "{0, 0.33628400935220848}",
      "hasCurveFrom": true,
      "hasCurveTo": false,
      "point": "{0, 0.33628400935220848}"
    }
  ],
  "resizingConstraint": 63,
  "resizingType": 0,
  "rotation": 0,
  "shouldBreakMaskChain": false,
  "style": {
    "_class": "style",
    "blur": {
      "_class": "blur",
      "center": "{0.5, 0.5}",
      "do_objectID": "CEEA60E1-8C49-4D56-9C07-8D0E6165EF89",
      "isEnabled": false,
      "motionAngle": 0,
      "radius": 10,
      "saturation": 1,
      "type": 0
    },
    "borderOptions": {
      "_class": "borderOptions",
      "dashPattern": [
      ],
      "do_objectID": "A018086A-103B-4B27-98D3-18806CFF3E98",
      "isEnabled": true,
      "lineCapStyle": 0,
      "lineJoinStyle": 0
    },
    "borders": [
    ],
    "colorControls": {
      "_class": "colorControls",
      "brightness": 0,
      "contrast": 1,
      "do_objectID": "D0F4BC1D-037F-4371-9E29-C8161984A179",
      "hue": 0,
      "isEnabled": true,
      "saturation": 1
    },
    "contextSettings": {
      "_class": "graphicsContextSettings",
      "blendMode": 0,
      "do_objectID": "8889C555-2DEA-43D2-8649-EC15F8738A00",
      "opacity": 1
    },
    "do_objectID": "FC333645-C8D2-4B29-9265-03CDB61EF9E2",
    "endMarkerType": 0,
    "fills": [
      {
        "_class": "fill",
        "color": {
          "_class": "color",
          "alpha": 1,
          "blue": 0.4352941176470588,
          "green": 0.4352941176470588,
          "red": 0.4352941176470588
        },
        "contextSettings": {
          "_class": "graphicsContextSettings",
          "blendMode": 0,
          "opacity": 1
        },
        "fillType": 0,
        "gradient": {
          "_class": "gradient",
          "elipseLength": 0,
          "from": "{0.5, 0}",
          "gradientType": 0,
          "stops": [
            {
              "_class": "gradientStop",
              "color": {
                "_class": "color",
                "alpha": 1,
                "blue": 1,
                "green": 1,
                "red": 1
              },
              "position": 0
            },
            {
              "_class": "gradientStop",
              "color": {
                "_class": "color",
                "alpha": 1,
                "blue": 0,
                "green": 0,
                "red": 0
              },
              "position": 1
            }
          ],
          "to": "{0.5, 1}"
        },
        "isEnabled": true,
        "noiseIndex": 0,
        "noiseIntensity": 0,
        "patternFillType": 1,
        "patternTileScale": 1
      }
    ],
    "innerShadows": [
    ],
    "miterLimit": 10,
    "shadows": [
    ],
    "startMarkerType": 0,
    "windingRule": 0
  }
}