{
  "_class": "symbolMaster",
  "allowsOverrides": true,
  "backgroundColor": {
    "_class": "color",
    "alpha": 1,
    "blue": 1,
    "green": 1,
    "red": 1
  },
  "booleanOperation": -1,
  "changeIdentifier": 2827,
  "clippingMaskMode": 0,
  "do_objectID": "E0D3BDC1-1820-4B60-92F1-7A31AA0CAE08",
  "exportOptions": {
    "_class": "exportOptions",
    "exportFormats": [
    ],
    "includedLayerIds": [
    ],
    "layerOptions": 0,
    "shouldTrim": false
  },
  "frame": {
    "_class": "rect",
    "constrainProportions": false,
    "height": 53,
    "width": 1440,
    "x": 2207,
    "y": 0
  },
  "groupLayout": {
    "_class": "MSImmutableFreeformGroupLayout"
  },
  "hasBackgroundColor": false,
  "hasClickThrough": true,
  "hasClippingMask": false,
  "horizontalRulerData": {
    "_class": "rulerData",
    "base": 0,
    "guides": [
    ]
  },
  "includeBackgroundColorInExport": true,
  "includeBackgroundColorInInstance": false,
  "includeInCloudUpload": true,
  "isFixedToViewport": false,
  "isFlippedHorizontal": false,
  "isFlippedVertical": false,
  "isFlowHome": false,
  "isLocked": false,
  "isVisible": true,
  "layerListExpandedType": 2,
  "layers": [
    {
      "class": "rectangle",
      "id": "A303030A-5C7E-45A6-9014-626E7CE15A06"
    },
    {
      "class": "oval",
      "id": "5611C85A-5A13-4D9C-A41B-F8952167630F"
    },
    {
      "class": "triangle",
      "id": "07A9CC38-99B4-4C00-A78D-2D5A6105A175"
    },
    {
      "class": "rectangle",
      "id": "C8FA73D1-ED40-41B2-917E-7A29B6F896C1"
    },
    {
      "class": "triangle",
      "id": "3FF89825-E86A-46D3-B80F-0169794A8D54"
    },
    {
      "class": "rectangle",
      "id": "14C39898-5CEB-424D-9413-4229A9B7E6DC"
    },
    {
      "class": "text",
      "id": "B4D476D1-8BCB-448F-99F1-2F52D5F56EDE"
    },
    {
      "class": "text",
      "id": "621EBDA5-E8F0-4BAB-A0E6-CF54E452207F"
    },
    {
      "class": "rectangle",
      "id": "46EB0904-6C06-4CA0-AA4F-AC2B1F1D0163"
    },
    {
      "class": "rectangle",
      "id": "47B37500-0F17-4F12-92D4-77184B11C955"
    },
    {
      "class": "group",
      "id": "BF3755A5-49B8-4A95-B79A-DE816959AF63"
    },
    {
      "class": "bitmap",
      "id": "EE8C4B96-10F7-4AB7-835E-9CEA04F3FEDB"
    },
    {
      "class": "rectangle",
      "id": "8951929E-142E-4CF8-B1B2-86E26AE31320"
    },
    {
      "class": "rectangle",
      "id": "80A56A10-0E45-4243-8CC4-353EF5F4821F"
    },
    {
      "class": "oval",
      "id": "E33B7739-4CE5-4441-94D8-68D509203C28"
    }
  ],
  "layout": {
    "_class": "layoutGrid",
    "columnWidth": 60,
    "drawHorizontal": false,
    "drawHorizontalLines": false,
    "drawVertical": true,
    "gutterHeight": 12,
    "gutterWidth": 20,
    "guttersOutside": true,
    "horizontalOffset": 240,
    "isEnabled": false,
    "numberOfColumns": 12,
    "rowHeightMultiplication": 5,
    "totalWidth": 960
  },
  "name": "musicplayer",
  "nameIsFixed": false,
  "overrideProperties": [
    {
      "_class": "MSImmutableOverrideProperty",
      "canOverride": true,
      "overrideName": "E33B7739-4CE5-4441-94D8-68D509203C28_layerStyle"
    },
    {
      "_class": "MSImmutableOverrideProperty",
      "canOverride": true,
      "overrideName": "46EB0904-6C06-4CA0-AA4F-AC2B1F1D0163_layerStyle"
    },
    {
      "_class": "MSImmutableOverrideProperty",
      "canOverride": true,
      "overrideName": "47B37500-0F17-4F12-92D4-77184B11C955_layerStyle"
    },
    {
      "_class": "MSImmutableOverrideProperty",
      "canOverride": true,
      "overrideName": "EE8C4B96-10F7-4AB7-835E-9CEA04F3FEDB_image"
    },
    {
      "_class": "MSImmutableOverrideProperty",
      "canOverride": true,
      "overrideName": "CCDD577C-EE2B-43AC-958D-3EC7A8A5B62F_stringValue"
    },
    {
      "_class": "MSImmutableOverrideProperty",
      "canOverride": true,
      "overrideName": "E33B7739-4CE5-4441-94D8-68D509203C28_image"
    },
    {
      "_class": "MSImmutableOverrideProperty",
      "canOverride": true,
      "overrideName": "B4D476D1-8BCB-448F-99F1-2F52D5F56EDE_stringValue"
    },
    {
      "_class": "MSImmutableOverrideProperty",
      "canOverride": true,
      "overrideName": "BBDC2EE9-177C-4EC1-AF9E-DA8EDA2FFA3E_stringValue"
    },
    {
      "_class": "MSImmutableOverrideProperty",
      "canOverride": true,
      "overrideName": "621EBDA5-E8F0-4BAB-A0E6-CF54E452207F_stringValue"
    }
  ],
  "resizesContent": false,
  "resizingConstraint": 63,
  "resizingType": 0,
  "rotation": 0,
  "shouldBreakMaskChain": true,
  "style": {
    "_class": "style",
    "endMarkerType": 0,
    "miterLimit": 10,
    "startMarkerType": 0,
    "windingRule": 1
  },
  "symbolID": "8CC7B090-5C92-4E0F-A26C-3819292743B6",
  "verticalRulerData": {
    "_class": "rulerData",
    "base": 0,
    "guides": [
    ]
  }
}