{
  "_class": "symbolInstance",
  "booleanOperation": -1,
  "clippingMaskMode": 0,
  "do_objectID": "8AA8775D-7F24-4F5C-96FB-8CA7E413F25F",
  "exportOptions": {
    "_class": "exportOptions",
    "do_objectID": "2F96B760-710A-4F32-BCE0-1151CFA27C9F",
    "exportFormats": [
    ],
    "includedLayerIds": [
    ],
    "layerOptions": 0,
    "shouldTrim": false
  },
  "frame": {
    "_class": "rect",
    "constrainProportions": false,
    "do_objectID": "50F7A447-5358-468C-8239-4DFC7741C96F",
    "height": 100,
    "width": 960,
    "x": 0,
    "y": 792
  },
  "hasClippingMask": false,
  "horizontalSpacing": 0,
  "isFixedToViewport": false,
  "isFlippedHorizontal": false,
  "isFlippedVertical": false,
  "isLocked": false,
  "isVisible": true,
  "layerListExpandedType": 2,
  "name": "wireframes/concerts/entry",
  "nameIsFixed": false,
  "overrideValues": [
    {
      "_class": "overrideValue",
      "do_objectID": "81A752F9-9E26-4D03-915C-C97839B96CB0",
      "overrideName": "76C36C07-AF20-4C86-BA7D-28CED166AE0A_stringValue",
      "value": "Tickets"
    },
    {
      "_class": "overrideValue",
      "do_objectID": "24ABA48E-D1FF-4ACD-AAD2-9B8E02F2F471",
      "overrideName": "BAFFEF19-8CC2-4F5C-A317-35787A03FFFD_stringValue",
      "value": "Wien (AUT)"
    },
    {
      "_class": "overrideValue",
      "do_objectID": "C1205233-1DFF-4DDB-935C-6CBA8D8865AF",
      "overrideName": "DCB774BC-CAFC-4FE0-9275-72EC6BDBF923_stringValue",
      "value": "Konzerthaus"
    },
    {
      "_class": "overrideValue",
      "do_objectID": "A65D1BE2-D050-4801-A7BF-58694731A6F4",
      "overrideName": "0960D60B-B248-48B5-8676-114192192826_stringValue",
      "value": "25"
    },
    {
      "_class": "overrideValue",
      "do_objectID": "5B813F09-6F7B-463C-A792-78787AC7D8BD",
      "overrideName": "3BD5F38F-1EF0-41D2-B342-CF6019ABE437_stringValue",
      "value": "So"
    },
    {
      "_class": "overrideValue",
      "do_objectID": "E3772894-2489-49B8-BB26-D6F653759047",
      "overrideName": "DBFC1B13-BAF5-4375-BB0C-B9D64F116F5E_stringValue",
      "value": "Jul"
    }
  ],
  "resizingConstraint": 63,
  "resizingType": 0,
  "rotation": 0,
  "scale": 1,
  "shouldBreakMaskChain": false,
  "style": {
    "_class": "style",
    "do_objectID": "06D24293-51FC-400B-9F0D-4315DDC96938",
    "endMarkerType": 0,
    "miterLimit": 10,
    "startMarkerType": 0,
    "windingRule": 1
  },
  "symbolID": "B735924D-9667-41B6-9A9A-5DE5464B5CA6",
  "verticalSpacing": 0
}