{
  "_class": "symbolInstance",
  "booleanOperation": -1,
  "clippingMaskMode": 0,
  "do_objectID": "94F79E53-EFA5-42DD-BA70-6D4331A3AC4D",
  "exportOptions": {
    "_class": "exportOptions",
    "do_objectID": "A3C59940-3A14-49A5-ABE5-84BED11008F9",
    "exportFormats": [
    ],
    "includedLayerIds": [
    ],
    "layerOptions": 0,
    "shouldTrim": false
  },
  "frame": {
    "_class": "rect",
    "constrainProportions": false,
    "do_objectID": "0D81A96A-4CE8-435D-9D18-9A37A654F14E",
    "height": 50,
    "width": 226,
    "x": 730,
    "y": 5817
  },
  "hasClippingMask": false,
  "horizontalSpacing": 0,
  "isFixedToViewport": false,
  "isFlippedHorizontal": false,
  "isFlippedVertical": false,
  "isLocked": false,
  "isVisible": true,
  "layerListExpandedType": 0,
  "name": "ui/button/primary",
  "nameIsFixed": false,
  "overrideValues": [
    {
      "_class": "overrideValue",
      "do_objectID": "E940FBDB-1201-4D15-898E-ED1A829EFEE0",
      "overrideName": "1F2EE244-66A4-47E0-99A6-321BB3D2D447_stringValue",
      "value": "Jetzt kaufen"
    },
    {
      "_class": "overrideValue",
      "do_objectID": "F50CA59C-1DDA-4DBF-8D29-3252FEC0B411",
      "overrideName": "BD851650-D9F9-4237-876B-51CA833F5106_layerStyle",
      "value": "45DE90B0-8046-4FB3-BD1E-E91182A38896"
    }
  ],
  "resizingConstraint": 63,
  "resizingType": 0,
  "rotation": 0,
  "scale": 1,
  "shouldBreakMaskChain": false,
  "style": {
    "_class": "style",
    "do_objectID": "C9CD95F7-A5D2-42FE-895D-21689656C64F",
    "endMarkerType": 0,
    "miterLimit": 10,
    "startMarkerType": 0,
    "windingRule": 1
  },
  "symbolID": "08D52534-5376-4BAA-85BF-D3965667E559",
  "verticalSpacing": 0
}